flowmap/__init__.py
flowmap/cli.py
flowmap/dem.py
flowmap/flowmap.py
flowmap/particles.py
flowmap/subgrid.py
flowmap/topology.py
flowmap/formats/__init__.py
flowmap/formats/delft3d.py
flowmap/formats/formats.py
flowmap/formats/json_encoder.py
flowmap/formats/matroos.py
flowmap/formats/netcdf.py
flowmap/formats/ugrid.py
flowmap-1.0.0.data/scripts/matroos_flowmap
flowmap-1.0.0.dist-info/DESCRIPTION.rst
flowmap-1.0.0.dist-info/METADATA
flowmap-1.0.0.dist-info/RECORD
flowmap-1.0.0.dist-info/WHEEL
flowmap-1.0.0.dist-info/entry_points.txt
flowmap-1.0.0.dist-info/metadata.json
flowmap-1.0.0.dist-info/top_level.txt
tests/__init__.py
tests/test_flowmap.py
tests/test_particles.py
tests/test_subgrid.py
