Metadata-Version: 2.0
Name: flowmap
Version: 1.0.0
Summary: Command line utility to transform model output into a flowmap that can be used for games or gpu-based visualizations.
Home-page: https://github.com/SiggyF/flowmap
Author: Fedor Baart
Author-email: fedor.baart@deltares.nl
License: GNU General Public License v3
Keywords: flowmap
Platform: UNKNOWN
Classifier: Development Status :: 4 - Beta
Classifier: Intended Audience :: Developers
Classifier: License :: OSI Approved :: GNU General Public License v3 or later (GPLv3+)
Classifier: Natural Language :: English
Classifier: Programming Language :: Python :: 3
Classifier: Programming Language :: Python :: 3.5
Classifier: Programming Language :: Python :: 3.6
